hyperparam/__init__.py
hyperparam/hyp.py
hyperparam-0.1.0.dist-info/LICENSE
hyperparam-0.1.0.dist-info/METADATA
hyperparam-0.1.0.dist-info/WHEEL
hyperparam-0.1.0.dist-info/entry_points.txt
hyperparam-0.1.0.dist-info/top_level.txt
hyperparam-0.1.0.dist-info/RECORD
