Metadata-Version: 2.1
Name: hyperparam
Version: 0.1.0
Summary: A description of your package
Author-email: Hyperparam <kenny@hyperparam.app>
License: MIT
Project-URL: Homepage, https://github.com/hyparam/pypyrpyram
Classifier: Programming Language :: Python :: 3
Classifier: License :: OSI Approved :: MIT License
Classifier: Operating System :: OS Independent
License-File: LICENSE
Requires-Dist: wheel
